sample/__init__.py
sample/hello.py
kishans_sample_hello-1.0.0.dist-info/LICENSE.txt
kishans_sample_hello-1.0.0.dist-info/METADATA
kishans_sample_hello-1.0.0.dist-info/WHEEL
kishans_sample_hello-1.0.0.dist-info/entry_points.txt
kishans_sample_hello-1.0.0.dist-info/top_level.txt
kishans_sample_hello-1.0.0.dist-info/RECORD
